src/api.py
src/cli.py
src/constants.py
src/deployment.py
src/utils.py
glide_cli-0.1.1.dist-info/LICENSE
glide_cli-0.1.1.dist-info/METADATA
glide_cli-0.1.1.dist-info/WHEEL
glide_cli-0.1.1.dist-info/entry_points.txt
glide_cli-0.1.1.dist-info/top_level.txt
glide_cli-0.1.1.dist-info/RECORD
